Workbook

Sheet Dough Cost
A1: OH, CHEWY! – COOKIE DOUGH COST CALCULATOR
A2: Enter the quantities used in one batch and the package prices. Blue cells are inputs; black cells calculate automatically.
A4: Batch Settings
A5: Cookies produced per batch | B5: 0 | D5: Dough weight per cookie (g) | E5: 70
A6: Unsellable/test cookies per batch | B6: 0 | D6: Waste allowance | E6: 0.05
A7: Sellable cookies per batch | B7: =MAX(B5-B6,0) -> 0 | D7: Classic selling price (JOD) | E7: 1
A10: Ingredient | B10: Quantity used / batch | C10: Unit | D10: Package quantity | E10: Package unit | F10: Package price (JOD) | G10: Cost per unit | H10: Batch ingredient cost | I10: Cost incl. waste | J10: Notes
A11: Butter | B11: 0 | C11: g | D11: 0 | E11: g | F11: 0 | G11: =IFERROR(F11/D11,0) -> 0 | H11: =B11*G11 -> 0 | I11: =H11*(1+$E$6) -> 0
A12: Brown sugar | B12: 0 | C12: g | D12: 0 | E12: g | F12: 0 | G12: =IFERROR(F12/D12,0) -> 0 | H12: =B12*G12 -> 0 | I12: =H12*(1+$E$6) -> 0
A13: Granulated sugar | B13: 0 | C13: g | D13: 0 | E13: g | F13: 0 | G13: =IFERROR(F13/D13,0) -> 0 | H13: =B13*G13 -> 0 | I13: =H13*(1+$E$6) -> 0
A14: Flour | B14: 0 | C14: g | D14: 0 | E14: g | F14: 0 | G14: =IFERROR(F14/D14,0) -> 0 | H14: =B14*G14 -> 0 | I14: =H14*(1+$E$6) -> 0
A15: Eggs | B15: 0 | C15: g | D15: 0 | E15: g | F15: 0 | G15: =IFERROR(F15/D15,0) -> 0 | H15: =B15*G15 -> 0 | I15: =H15*(1+$E$6) -> 0
A16: Baking soda | B16: 0 | C16: g | D16: 0 | E16: g | F16: 0 | G16: =IFERROR(F16/D16,0) -> 0 | H16: =B16*G16 -> 0 | I16: =H16*(1+$E$6) -> 0
A17: Baking powder | B17: 0 | C17: g | D17: 0 | E17: g | F17: 0 | G17: =IFERROR(F17/D17,0) -> 0 | H17: =B17*G17 -> 0 | I17: =H17*(1+$E$6) -> 0
A18: Vanilla | B18: 0 | C18: g | D18: 0 | E18: g | F18: 0 | G18: =IFERROR(F18/D18,0) -> 0 | H18: =B18*G18 -> 0 | I18: =H18*(1+$E$6) -> 0
A19: Salt | B19: 0 | C19: g | D19: 0 | E19: g | F19: 0 | G19: =IFERROR(F19/D19,0) -> 0 | H19: =B19*G19 -> 0 | I19: =H19*(1+$E$6) -> 0
A20: Cocoa powder (if in base) | B20: 0 | C20: g | D20: 0 | E20: g | F20: 0 | G20: =IFERROR(F20/D20,0) -> 0 | H20: =B20*G20 -> 0 | I20: =H20*(1+$E$6) -> 0
A21: Milk / cream (if used) | B21: 0 | C21: g | D21: 0 | E21: g | F21: 0 | G21: =IFERROR(F21/D21,0) -> 0 | H21: =B21*G21 -> 0 | I21: =H21*(1+$E$6) -> 0
A22: Cornstarch (if used) | B22: 0 | C22: g | D22: 0 | E22: g | F22: 0 | G22: =IFERROR(F22/D22,0) -> 0 | H22: =B22*G22 -> 0 | I22: =H22*(1+$E$6) -> 0
... A24: Other base ingredient 2 | B24: 0 | C24: g | D24: 0 | E24: g | F24: 0 | G24: =IFERROR(F24/D24,0) -> 0 | H24: =B24*G24 -> 0 | I24: =H24*(1+$E$6) -> 0
A25: TOTAL BASE DOUGH COST / BATCH | I25: =SUM(I11:I24) -> 0
A27: CLASSIC COOKIE PRICE CHECK
A28: Base dough cost per sellable cookie | E28: =IFERROR(I25/$B$7,0) -> 0
A29: Base dough cost per gram | E29: =IFERROR(I25/($B$5*$E$5),0) -> 0
A30: Classic additions cost per cookie | E30: ='Flavor Costs'!H5 -> 0
A31: Production/overhead per cookie | E31: ='Production Costs'!F18 -> 0
A32: Single-cookie packaging cost | E32: =Packaging!F19 -> 0
A33: TOTAL CLASSIC COST PER COOKIE | E33: =SUM(E28:E32) -> 0
A34: Profit per Classic cookie | E34: =$E$7-E33 -> 1
A35: Cost as % of selling price | E35: =IFERROR(E33/$E$7,0) -> 0
A36: Gross margin % | E36: =IFERROR(E34/$E$7,0) -> 1
A37: Price check | E37: =IF(E33<$E$7,"PASS – cost is below 1 JOD","REVIEW – cost reaches/exceeds 1 JOD") -> PASS – cost is below 1 JOD

Sheet Flavor Costs
A1: FLAVOR ADDITIONS COST PER COOKIE
A3: Flavor | B3: Addition | C3: Grams per cookie | D3: Package grams | E3: Package price (JOD) | F3: Cost per gram | G3: Cost per cookie | H3: Flavor total
A4: Classic | B4: Chocolate chips | C4: 0 | D4: 0 | E4: 0 | F4: =IFERROR(E4/D4,0) -> 0 | G4: =C4*F4 -> 0 | H4: =SUM(G4:G5) -> 0
A5: Classic | B5: Other topping | C5: 0 | D5: 0 | E5: 0 | F5: =IFERROR(E5/D5,0) -> 0 | G5: =C5*F5 -> 0
A6: Double Chocolate | B6: Cocoa powder | C6: 0 | D6: 0 | E6: 0 | F6: =IFERROR(E6/D6,0) -> 0 | G6: =C6*F6 -> 0 | H6: =SUM(G6:G8) -> 0
A7: Double Chocolate | B7: Chocolate chunks | C7: 0 | D7: 0 | E7: 0 | F7: =IFERROR(E7/D7,0) -> 0 | G7: =C7*F7 -> 0
A8: Double Chocolate | B8: Other topping | C8: 0 | D8: 0 | E8: 0 | F8: =IFERROR(E8/D8,0) -> 0 | G8: =C8*F8 -> 0
A9: Lotus Biscoff | B9: Lotus spread filling | C9: 0 | D9: 0 | E9: 0 | F9: =IFERROR(E9/D9,0) -> 0 | G9: =C9*F9 -> 0 | H9: =SUM(G9:G11) -> 0
A10: Lotus Biscoff | B10: Lotus biscuit | C10: 0 | D10: 0 | E10: 0 | F10: =IFERROR(E10/D10,0) -> 0 | G10: =C10*F10 -> 0
A11: Lotus Biscoff | B11: Chocolate / topping | C11: 0 | D11: 0 | E11: 0 | F11: =IFERROR(E11/D11,0) -> 0 | G11: =C11*F11 -> 0
A12: Pistachio | B12: Pistachio cream filling | C12: 0 | D12: 0 | E12: 0 | F12: =IFERROR(E12/D12,0) -> 0 | G12: =C12*F12 -> 0 | H12: =SUM(G12:G14) -> 0
A13: Pistachio | B13: Pistachio pieces | C13: 0 | D13: 0 | E13: 0 | F13: =IFERROR(E13/D13,0) -> 0 | G13: =C13*F13 -> 0
A14: Pistachio | B14: Chocolate / topping | C14: 0 | D14: 0 | E14: 0 | F14: =IFERROR(E14/D14,0) -> 0 | G14: =C14*F14 -> 0
A15: Red Velvet | B15: Cocoa powder | C15: 0 | D15: 0 | E15: 0 | F15: =IFERROR(E15/D15,0) -> 0 | G15: =C15*F15 -> 0 | H15: =SUM(G15:G18) -> 0
A16: Red Velvet | B16: Red coloring | C16: 0 | D16: 0 | E16: 0 | F16: =IFERROR(E16/D16,0) -> 0 | G16: =C16*F16 -> 0
A17: Red Velvet | B17: White chocolate | C17: 0 | D17: 0 | E17: 0 | F17: =IFERROR(E17/D17,0) -> 0 | G17: =C17*F17 -> 0
A18: Red Velvet | B18: Cream cheese / filling | C18: 0 | D18: 0 | E18: 0 | F18: =IFERROR(E18/D18,0) -> 0 | G18: =C18*F18 -> 0

Sheet Production Costs
A1: PRODUCTION, LABOR & OVERHEAD COSTS
A3: Cost item | B3: Quantity / time | C3: Unit | D3: Rate / unit (JOD) | E3: Batch cost (JOD) | F3: Cost per sellable cookie
A4: Oven electricity / gas | B4: 1 | C4: batch | D4: 0 | E4: =B4*D4 -> 0 | F4: =IFERROR(E4/'Dough Cost'!$B$7,0) -> 0
A5: Mixer electricity | B5: 1 | C5: batch | D5: 0 | E5: =B5*D5 -> 0 | F5: =IFERROR(E5/'Dough Cost'!$B$7,0) -> 0
A6: Refrigerator/freezer allocation | B6: 1 | C6: batch | D6: 0 | E6: =B6*D6 -> 0 | F6: =IFERROR(E6/'Dough Cost'!$B$7,0) -> 0
A7: Preparation labor | B7: 0 | C7: hours | D7: 0 | E7: =B7*D7 -> 0 | F7: =IFERROR(E7/'Dough Cost'!$B$7,0) -> 0
A8: Portioning/filling labor | B8: 0 | C8: hours | D8: 0 | E8: =B8*D8 -> 0 | F8: =IFERROR(E8/'Dough Cost'!$B$7,0) -> 0
A9: Baking/cooling labor | B9: 0 | C9: hours | D9: 0 | E9: =B9*D9 -> 0 | F9: =IFERROR(E9/'Dough Cost'!$B$7,0) -> 0
A10: Packing/cleaning labor | B10: 0 | C10: hours | D10: 0 | E10: =B10*D10 -> 0 | F10: =IFERROR(E10/'Dough Cost'!$B$7,0) -> 0
A11: Cleaning supplies | B11: 1 | C11: batch | D11: 0 | E11: =B11*D11 -> 0 | F11: =IFERROR(E11/'Dough Cost'!$B$7,0) -> 0
A12: Gloves / hair covers | B12: 1 | C12: batch | D12: 0 | E12: =B12*D12 -> 0 | F12: =IFERROR(E12/'Dough Cost'!$B$7,0) -> 0
A13: Equipment depreciation | B13: 1 | C13: batch | D13: 0 | E13: =B13*D13 -> 0 | F13: =IFERROR(E13/'Dough Cost'!$B$7,0) -> 0
A14: Kitchen/rent allocation | B14: 1 | C14: batch | D14: 0 | E14: =B14*D14 -> 0 | F14: =IFERROR(E14/'Dough Cost'!$B$7,0) -> 0
A15: Marketing/samples allocation | B15: 1 | C15: batch | D15: 0 | E15: =B15*D15 -> 0 | F15: =IFERROR(E15/'Dough Cost'!$B$7,0) -> 0
... A17: Other overhead | B17: 1 | C17: batch | D17: 0 | E17: =B17*D17 -> 0 | F17: =IFERROR(E17/'Dough Cost'!$B$7,0) -> 0
A18: TOTAL | E18: =SUM(E4:E17) -> 0 | F18: =SUM(F4:F17) -> 0

Sheet Packaging
A1: PACKAGING COSTS
A3: Packaging item | B3: Units purchased | C3: Package price (JOD) | D3: Cost per unit | E3: Units used per order | F3: Cost per order | G3: Notes
A4: Single-cookie bag/wrap | B4: 0 | C4: 0 | D4: =IFERROR(C4/B4,0) -> 0 | E4: 1 | F4: =D4*E4 -> 0
A5: Flavor sticker | B5: 0 | C5: 0 | D5: =IFERROR(C5/B5,0) -> 0 | E5: 1 | F5: =D5*E5 -> 0
A6: Logo/sealing sticker | B6: 0 | C6: 0 | D6: =IFERROR(C6/B6,0) -> 0 | E6: 1 | F6: =D6*E6 -> 0
A7: Baking paper allocation | B7: 0 | C7: 0 | D7: =IFERROR(C7/B7,0) -> 0 | E7: 1 | F7: =D7*E7 -> 0
A8: Box – 5 cookies | B8: 0 | C8: 0 | D8: =IFERROR(C8/B8,0) -> 0 | E8: 0 | F8: =D8*E8 -> 0
A9: Box – 10 cookies | B9: 0 | C9: 0 | D9: =IFERROR(C9/B9,0) -> 0 | E9: 0 | F9: =D9*E9 -> 0
A10: Box – 15 cookies | B10: 0 | C10: 0 | D10: =IFERROR(C10/B10,0) -> 0 | E10: 0 | F10: =D10*E10 -> 0
A11: Box – 20 cookies | B11: 0 | C11: 0 | D11: =IFERROR(C11/B11,0) -> 0 | E11: 0 | F11: =D11*E11 -> 0
A12: Ingredient/allergen label | B12: 0 | C12: 0 | D12: =IFERROR(C12/B12,0) -> 0 | E12: 0 | F12: =D12*E12 -> 0
A13: Production-date label | B13: 0 | C13: 0 | D13: =IFERROR(C13/B13,0) -> 0 | E13: 0 | F13: =D13*E13 -> 0
A14: Thank-you card | B14: 0 | C14: 0 | D14: =IFERROR(C14/B14,0) -> 0 | E14: 0 | F14: =D14*E14 -> 0
A15: Paper bag | B15: 0 | C15: 0 | D15: =IFERROR(C15/B15,0) -> 0 | E15: 0 | F15: =D15*E15 -> 0
... A17: Other packaging | B17: 0 | C17: 0 | D17: =IFERROR(C17/B17,0) -> 0 | E17: 0 | F17: =D17*E17 -> 0
A19: Single-cookie packaging subtotal | F19: =SUM(F4:F7) -> 0

Sheet Pricing Summary
A1: OH, CHEWY! – COST & PRICING SUMMARY
A3: Flavor | B3: Base dough | C3: Flavor additions | D3: Production/overhead | E3: Single packaging | F3: Total cost | G3: Current price | H3: Profit | I3: Cost % of price
A4: Classic | B4: ='Dough Cost'!$E$28 -> 0 | C4: ='Flavor Costs'!H4 -> 0 | D4: ='Production Costs'!$F$18 -> 0 | E4: =Packaging!$F$19 -> 0 | F4: =SUM(B4:E4) -> 0 | G4: 1 | H4: =G4-F4 -> 1 | I4: =IFERROR(F4/G4,0) -> 0
A5: Double Chocolate | B5: ='Dough Cost'!$E$28 -> 0 | C5: ='Flavor Costs'!H6 -> 0 | D5: ='Production Costs'!$F$18 -> 0 | E5: =Packaging!$F$19 -> 0 | F5: =SUM(B5:E5) -> 0 | G5: 1 | H5: =G5-F5 -> 1 | I5: =IFERROR(F5/G5,0) -> 0
A6: Lotus Biscoff | B6: ='Dough Cost'!$E$28 -> 0 | C6: ='Flavor Costs'!H9 -> 0 | D6: ='Production Costs'!$F$18 -> 0 | E6: =Packaging!$F$19 -> 0 | F6: =SUM(B6:E6) -> 0 | G6: 1.25 | H6: =G6-F6 -> 1.25 | I6: =IFERROR(F6/G6,0) -> 0
A7: Pistachio | B7: ='Dough Cost'!$E$28 -> 0 | C7: ='Flavor Costs'!H12 -> 0 | D7: ='Production Costs'!$F$18 -> 0 | E7: =Packaging!$F$19 -> 0 | F7: =SUM(B7:E7) -> 0 | G7: 1.25 | H7: =G7-F7 -> 1.25 | I7: =IFERROR(F7/G7,0) -> 0
A8: Red Velvet | B8: ='Dough Cost'!$E$28 -> 0 | C8: ='Flavor Costs'!H15 -> 0 | D8: ='Production Costs'!$F$18 -> 0 | E8: =Packaging!$F$19 -> 0 | F8: =SUM(B8:E8) -> 0 | G8: 1.25 | H8: =G8-F8 -> 1.25 | I8: =IFERROR(F8/G8,0) -> 0
A11: BOX PRICE CALCULATOR
A12: Box size | B12: Classic qty | C12: Double Choc qty | D12: Lotus qty | E12: Pistachio qty | F12: Red Velvet qty | G12: Cookie cost | H12: Box packaging | I12: Total box cost
A13: 5 | B13: 0 | C13: 0 | D13: 0 | E13: 0 | F13: 0 | G13: =B13*$F$4+C13*$F$5+D13*$F$6+E13*$F$7+F13*$F$8 -> 0 | H13: =Packaging!F8 -> 0 | I13: =G13+H13 -> 0
A14: 10 | B14: 0 | C14: 0 | D14: 0 | E14: 0 | F14: 0 | G14: =B14*$F$4+C14*$F$5+D14*$F$6+E14*$F$7+F14*$F$8 -> 0 | H14: =Packaging!F9 -> 0 | I14: =G14+H14 -> 0
A15: 15 | B15: 0 | C15: 0 | D15: 0 | E15: 0 | F15: 0 | G15: =B15*$F$4+C15*$F$5+D15*$F$6+E15*$F$7+F15*$F$8 -> 0 | H15: =Packaging!F10 -> 0 | I15: =G15+H15 -> 0
A16: 20 | B16: 0 | C16: 0 | D16: 0 | E16: 0 | F16: 0 | G16: =B16*$F$4+C16*$F$5+D16*$F$6+E16*$F$7+F16*$F$8 -> 0 | H16: =Packaging!F11 -> 0 | I16: =G16+H16 -> 0
